{
    "variable": {
        "S": {
            "next": [
                [
                    "CC",
                    "CD"
                ],
                [
                    "A",
                    "B"
                ],
                [
                    "CA",
                    "CB"
                ]
            ],
            "reg": null,
            "treat_as_word": true
        },
        "A": {
            "next": [],
            "reg": "^int$",
            "treat_as_word": true
        },
        "B": {
            "next": [
                [
                    "C",
                    "D"
                ]
            ],
            "reg": null,
            "treat_as_word": true
        },
        "CA": {
            "next": [],
            "reg": "^boolean$",
            "treat_as_word": true
        },
        "CB": {
            "next": [
                [
                    "C",
                    "CE"
                ]
            ],
            "reg": null,
            "treat_as_word": true
        },
        "CC": {
            "next": [],
            "reg": "^string$",
            "treat_as_word": true
        },
        "CD": {
            "next": [
                [
                    "C",
                    "CH"
                ]
            ],
            "reg": null,
            "treat_as_word": true
        },
        "C": {
            "next": [
                [
                    "LE",
                    "C"
                ],
                [
                    null
                ]
            ],
            "reg": null,
            "treat_as_word": false
        },
        "LE": {
            "next": [],
            "reg": "^[a-zA-Z]$",
            "treat_as_word": false
        },
        "CH": {
            "next": [
                [
                    "E",
                    "CJ"
                ]
            ],
            "reg": null,
            "treat_as_word": true
        },
        "E": {
            "next": [],
            "reg": "^=$",
            "treat_as_word": true
        },
        "CJ": {
            "next": [
                [
                    "G",
                    "CK"
                ]
            ],
            "reg": null,
            "treat_as_word": true
        },
        "G": {
            "next": [],
            "reg": "^\"$",
            "treat_as_word": true
        },
        "CK": {
            "next": [
                [
                    "C",
                    "CL"
                ]
            ],
            "reg": null,
            "treat_as_word": true
        },
        "CL": {
            "next": [
                [
                    "G",
                    "PC"
                ]
            ],
            "reg": null,
            "treat_as_word": true
        },
        "D": {
            "next": [
                [
                    "E",
                    "F"
                ]
            ],
            "reg": null,
            "treat_as_word": true
        },
        "CE": {
            "next": [
                [
                    "E",
                    "CF"
                ]
            ],
            "reg": null,
            "treat_as_word": true
        },
        
        "F": {
            "next": [
                [
                    "RD",
                    "PC"
                ]
            ],
            "reg": null,
            "treat_as_word": true
        },
        "CF": {
            "next": [
                [
                    "CG",
                    "PC"
                ]
            ],
            "reg": null,
            "treat_as_word": true
        },
        
        "RD": {
            "next": [
                [
                    "DI",
                    "RD"
                ],
                [
                    null
                ]
            ],
            "reg": null,
            "treat_as_word": true
        },
        "CG": {
            "next": [],
            "reg": "^(true|false)$",
            "treat_as_word": true
        },
        
        "DI": {
            "next": [],
            "reg": "^[0-9]$",
            "treat_as_word": false
        },
        "PC": {
            "next": [],
            "reg": "^;$",
            "treat_as_word": true,
            "last_transition": true
        }
    }, 
    "function": {
        "V": {
            "next": [
                [
                    "K",
                    "L"
                ]
            ],
            "reg": null,
            "treat_as_word": true,
            "last_transition": false
        },
        "K": {
            "next": [],
            "reg": "^func$",
            "treat_as_word": true,
            "last_transition": false
        },
        "L": {
            "next": [
                [
                    "G",
                    "M"
                ]
            ],
            "reg": null,
            "treat_as_word": true,
            "last_transition": false
        },
        "G": {
            "next": [],
            "reg": "^\"$",
            "treat_as_word": true
        },
        "M": {
            "next": [
                [
                    "C",
                    "N"
                ]
            ],
            "reg": null,
            "treat_as_word": true,
            "last_transition": false
        },
        "C": {
            "next": [
                [
                    "LE",
                    "C"
                ],
                [
                    null
                ]
            ],
            "reg": null,
            "treat_as_word": false
        },
        "LE": {
            "next": [],
            "reg": "^[a-zA-Z]$",
            "treat_as_word": false
        },
        "N": {
            "next": [
                [
                    "G",
                    "O"
                ]
            ],
            "reg": null,
            "treat_as_word": true,
            "last_transition": false
        },
        "O": {
            "next": [
                [
                    "PI",
                    "P"
                ]
            ],
            "reg": null,
            "treat_as_word": true,
            "last_transition": false
        },
        "PI": {
            "next": [
                []
            ],
            "reg": "^\\($",
            "treat_as_word": true
        },
        "P": {
            "next": [
                [
                    "PF",
                    "T"
                ],
                
                [
                    "C",
                    "R"
                ]
            ],
            "reg": null,
            "treat_as_word": true
        },
        "R": {
            "next": [
                [
                    "PF",
                    "T"
                ]
            ],
            "reg": null,
            "treat_as_word": false
        },
        "PF": {
            "next": [
                []
            ],
            "reg": "^\\)$",
            "treat_as_word": true
        },
        "T": {
            "next": [
                [
                    "CI",
                    "U"
                ]
            ],
            "reg": null,
            "treat_as_word": true
        },
        "CI": {
            "next": [],
            "reg": "^{$",
            "treat_as_word": true,
            "scopable": true,
            "last_transition": true
        },
        "U": {
            "next": [
                [
                    "CN",
                    "CF"
                ]
            ],
            "reg": null,
            "treat_as_word": true
        }
    },
    "conditional": {
        "W": {
            "next": [
                [
                    "X",
                    "Y"
                ]
            ],
            "reg": null,
            "treat_as_word": true
        },
        "X": {
            "next": [],
            "reg": "^if$",
            "treat_as_word": true
        },
        "Y": {
            "next": [
                [
                    "PI",
                    "Z"
                ]
            ],
            "reg": null,
            "treat_as_word": true
        },
        "PI": {
            "next": [],
            "reg": "^\\($",
            "treat_as_word": true
        },
        "Z": {
            "next": [
                [
                    "C",
                    "AB"
                ]
            ],
            "reg": null,
            "treat_as_word": true
        },
        "AB": {
            "next": [
                [
                    "OP",
                    "AC"
                ]
            ],
            "reg": null,
            "treat_as_word": true
        },
        "AC": {
            "next": [
                [
                    "CG",
                    "AD"
                ],
                [
                    "PA",
                    "AD"
                ]
            ],
            "reg": null,
            "treat_as_word": true
        },
        "AD": {
            "next": [
                [
                    "PF",
                    "LI"
                ],
                [
                    "PF",
                    "LI"
                ]
            ],
            "reg": null,
            "treat_as_word": true
        },
        "CG": {
            "next": [],
            "reg": "^(true|false)$",
            "treat_as_word": true
        },
        "OP": {
            "next": [],
            "reg": "^(>|<|==|!=)$",
            "treat_as_word": true
        },
        "PF": {
            "next": [
                []
            ],
            "reg": "^\\)$",
            "treat_as_word": true
            
        },
        "LI": {
            "next": [],
            "reg": "^{$",
            "treat_as_word": true,
            "last_transition": true,
            "scopable": true
        },
        "C": {
            "next": [
                [
                    "LE",
                    "C"
                ],
                [
                    null
                ]
            ],
            "reg": null,
            "treat_as_word": false
        },
        "LE": {
            "next": [],
            "reg": "^[a-zA-Z]$",
            "treat_as_word": false
        },
        "PA": {
            "next": [
                [
                    "L",
                    "PA"
                ],
                [
                    null
                ]
            ],
            "reg": null,
            "treat_as_word": false
        },
        "L": {
            "next": [],
            "reg": "^[a-zA-Z0-9]$",
            "treat_as_word": false
        }
        
        
    },
    "ciclos": {
        "AP": {
            "next": [
                [
                    "AQ",
                    "AR"
                ]
            ],
            "reg": null,
            "treat_as_word": true
        },
        "AQ": {
            "next": [],
            "reg": "^for$",
            "treat_as_word": true
        },
        "AR": {
            "next": [
                [
                    "PI",
                    "C1"
                ]
            ],
            "reg": null,
            "treat_as_word": true
        },
        "PI": {
            "next": [],
            "reg": "^\\($",
            "treat_as_word": true,
            "last_transition": true
        },
        "C1": {
            "next": [
                [
                    "AS",
                    "AV"
                ]
            ],
            "reg": null,
            "treat_as_word": true
        },
        "AS": {
            "next": [
                [
                    "A",
                    "AT"
                ]
            ],
            "reg": null,
            "treat_as_word": true
        },
        "A": {
            "next": [],
            "reg": "^int$",
            "treat_as_word": true
        },
        "AT": {
            "next": [
                [
                    "C",
                    "AU"
                ]
            ],
            "reg": null,
            "treat_as_word": true
        },
        "C": {
            "next": [
                [
                    "LE",
                    "C"
                ],
                [
                    null
                ]
            ],
            "reg": null,
            "treat_as_word": false
        },
        "LE": {
            "next": [],
            "reg": "^[a-zA-Z]$",
            "treat_as_word": false
        },
        "AU": {
            "next": [
                [
                    "E",
                    "C"
                ], 
                [
                    "E",
                    "RD"
                ]
            ],
            "reg": null,
            "treat_as_word": true
        },
        "E": {
            "next": [],
            "reg": "^=$",
            "treat_as_word": true
        },
        "RD": {
            "next": [
                [
                    "DI",
                    "RD"
                ],
                [
                    null
                ]
            ],
            "reg": null,
            "treat_as_word": true
        },
        "DI": {
            "next": [],
            "reg": "^[0-9]$",
            "treat_as_word": false
        },
        "AV": {
            "next": [
                [
                    "PC",
                    "C2"
                ]
            ],
            "reg": null,
            "treat_as_word": true
        },
        "PC": {
            "next": [],
            "reg": "^;$",
            "treat_as_word": true,
            "last_transition": true
        },
        "C2": {
            "next": [
                [
                    "AW",
                    "AZ"
                ]
            ],
            "reg": null,
            "treat_as_word": true
        },
        "AW": {
            "next": [
                [
                    "C",
                    "AX"
                ]
            ],
            "reg": null,
            "treat_as_word": true
        },
        "AX": {
            "next": [
                [
                    "AY",
                    "C"
                ]
            ],
            "reg": null,
            "treat_as_word": true
        },
        "AZ": {
            "next": [
                [
                    "PC",
                    "C3"
                ]
            ],
            "reg": null,
            "treat_as_word": true
        },
        "AY": {
            "next": [],
            "reg": "^(>|<|==|<=|>=)$",
            "treat_as_word": true
        },
        "C3": {
            "next": [
                [
                    "AS",
                    "AV"
                ]
            ],
            "reg": null,
            "treat_as_word": true
        },
        "BA": {
            "next": [
                [
                    "C",
                    "OF"
                ]
            ],
            "reg": null,
            "treat_as_word": true
        },
        "OF": {
            "next": [],
            "reg": "^(++|--)$",
            "treat_as_word": true
        },
        "BC": {
            "next": [
                [
                    "PC",
                    "BD"
                ]
            ],
            "reg": null,
            "treat_as_word": true
        },
        "BD": {
            "next": [
                [
                    "CI",
                    "BE"
                ]
            ],
            "reg": null,
            "treat_as_word": true
        },
        "BE": {
            "next": [
                [
                    "CN",
                    "CF"
                ]
            ],
            "reg": null,
            "treat_as_word": true
        }
    }
}